[
  {
    "formasi_id": "d87e5bd5-8214-4a57-b56e-de8dcaeb90d0",
    "ins_nm": "Pemerintah Kab. Fak-Fak",
    "jp_nama": "CPNS",
    "formasi_nm": "ORANG ASLI PAPUA (OAP)",
    "jabatan_nm": "PENATA SARANA DAN PRASARANA KELAUTAN DAN PERIKANAN",
    "lokasi_nm": "Pemerintah Kabupaten Fakfak | Dinas Perikanan dan Kelautan Kabupaten Fakfak | Bidang Budidaya Ikan dan Penyelenggaraan TPI | Seksi Analisis Penerbitan SIUP Budidaya Ikan",
    "jumlah_formasi": 4,
    "disable": 0,
    "gaji_min": "2500000",
    "gaji_max": "3500000",
    "jumlah_ms": 313,
    "kode_pend": "3110014",
    "nama_pend": "SMK ELEKTRONIKA"
  },
  {
    "formasi_id": "8a0384ba915598f401915600e1e23f41",
    "ins_nm": "Pemerintah Provinsi Papua Barat Daya",
    "jp_nama": "CPNS",
    "formasi_nm": "ORANG ASLI PAPUA (OAP)",
    "jabatan_nm": "PENATA SARANA DAN PRASARANA KELAUTAN DAN PERIKANAN",
    "lokasi_nm": "PEMERINTAH PROVINSI PAPUA BARAT DAYA | DINAS PERTANIAN, PANGAN, KELAUTAN DAN PERIKANAN | BIDANG KELAUTAN DAN PERIKANAN | SEKSI PENGELOLAAN RUANG LAUT",
    "jumlah_formasi": 1,
    "disable": 0,
    "gaji_min": "2498200",
    "gaji_max": "3498200",
    "jumlah_ms": 161,
    "kode_pend": "3110014",
    "nama_pend": "SMK ELEKTRONIKA"
  },
  {
    "formasi_id": "5a0eef0b-31c7-490b-ad21-0b8b319e5506",
    "ins_nm": "Pemerintah Provinsi Papua Barat Daya",
    "jp_nama": "CPNS",
    "formasi_nm": "UMUM (NON OAP)",
    "jabatan_nm": "PENATA SARANA DAN PRASARANA KELAUTAN DAN PERIKANAN",
    "lokasi_nm": "PEMERINTAH PROVINSI PAPUA BARAT DAYA | DINAS PERTANIAN, PANGAN, KELAUTAN DAN PERIKANAN | BIDANG KELAUTAN DAN PERIKANAN | SEKSI PENGELOLAAN RUANG LAUT",
    "jumlah_formasi": 1,
    "disable": 0,
    "gaji_min": "2498200",
    "gaji_max": "3498200",
    "jumlah_ms": 33,
    "kode_pend": "3110014",
    "nama_pend": "SMK ELEKTRONIKA"
  }
]