[
  {
    "formasi_id": "33de0ff6-a46a-4f5e-b622-06c21e5c0bd8",
    "ins_nm": "Otorita Ibu Kota Nusantara",
    "jp_nama": "CPNS",
    "formasi_nm": "UMUM",
    "jabatan_nm": "PENATA LAKSANA PENYEHATAN LINGKUNGAN PEMULA",
    "lokasi_nm": "OTORITA IBU KOTA NUSANTARA | DEPUTI BIDANG LINGKUNGAN HIDUP DAN SUMBER DAYA ALAM | DIREKTORAT LINGKUNGAN HIDUP DAN PENANGGULANGAN BENCANA",
    "jumlah_formasi": 1,
    "disable": 1,
    "gaji_min": "7500000",
    "gaji_max": "10000000",
    "jumlah_ms": 1461,
    "kode_pend": "3171087",
    "nama_pend": "SMK TEKNIK KONSTRUKSI BATU DAN BETON"
  },
  {
    "formasi_id": "af213d3f-2f7f-4a33-93de-4c6976aafe92",
    "ins_nm": "Pemerintah Kab. Halmahera Timur",
    "jp_nama": "CPNS",
    "formasi_nm": "UMUM",
    "jabatan_nm": "PENATA LAKSANA JALAN DAN JEMBATAN PEMULA",
    "lokasi_nm": "PEMERINTAH KAB. HALMAHERA TIMUR | DINAS PEKERJAAN UMUM DAN PENATAAN RUANG | BIDANG PEMBANGUNAN JALAN",
    "jumlah_formasi": 2,
    "disable": 1,
    "gaji_min": "2184000",
    "gaji_max": "3644000",
    "jumlah_ms": 14,
    "kode_pend": "3171087",
    "nama_pend": "SMK TEKNIK KONSTRUKSI BATU DAN BETON"
  },
  {
    "formasi_id": "cd1bf72e-4fbf-435f-9e3e-663c00bce87a",
    "ins_nm": "Pemerintah Kab. Halmahera Timur",
    "jp_nama": "CPNS",
    "formasi_nm": "UMUM",
    "jabatan_nm": "PENATA LAKSANA JALAN DAN JEMBATAN PEMULA",
    "lokasi_nm": "PEMERINTAH KAB. HALMAHERA TIMUR | DINAS PEKERJAAN UMUM DAN PENATAAN RUANG | BIDANG PEMBANGUNAN JEMBATAN",
    "jumlah_formasi": 3,
    "disable": 1,
    "gaji_min": "2184000",
    "gaji_max": "3644000",
    "jumlah_ms": 54,
    "kode_pend": "3171087",
    "nama_pend": "SMK TEKNIK KONSTRUKSI BATU DAN BETON"
  },
  {
    "formasi_id": "1d9d4bdd-14c3-4407-a442-dc55cbb0cd72",
    "ins_nm": "Pemerintah Kab. Jayawijaya",
    "jp_nama": "CPNS",
    "formasi_nm": "ORANG ASLI PAPUA (OAP)",
    "jabatan_nm": "PENATA LAKSANA PENYEHATAN LINGKUNGAN PEMULA",
    "lokasi_nm": "Kabupaten Jayawijaya | DINAS LINGKUNGAN HIDUP | BIDANG PENGENDALIAN PENCEMARAN & KERUSAKAN LINGKUNGAN HIDUP | SEKSI PEMANTAUAN LINGKUNGAN",
    "jumlah_formasi": 2,
    "disable": 1,
    "gaji_min": "2200000",
    "gaji_max": "4600000",
    "jumlah_ms": 64,
    "kode_pend": "3171087",
    "nama_pend": "SMK TEKNIK KONSTRUKSI BATU DAN BETON"
  },
  {
    "formasi_id": "8ca8c58c-957c-4dcd-94a6-98e58e1af548",
    "ins_nm": "Pemerintah Kab. Jayawijaya",
    "jp_nama": "CPNS",
    "formasi_nm": "ORANG ASLI PAPUA (OAP)",
    "jabatan_nm": "PENATA LAKSANA PENYEHATAN LINGKUNGAN PEMULA",
    "lokasi_nm": "Kabupaten Jayawijaya | DINAS LINGKUNGAN HIDUP | BIDANG TATA LINGKUNGAN | SEKSI PEMELIHARAAN LINGKUNGAN HIDUP",
    "jumlah_formasi": 2,
    "disable": 1,
    "gaji_min": "2200000",
    "gaji_max": "4600000",
    "jumlah_ms": 104,
    "kode_pend": "3171087",
    "nama_pend": "SMK TEKNIK KONSTRUKSI BATU DAN BETON"
  },
  {
    "formasi_id": "8e1d1325-af78-4dcb-9949-e0bd998e4810",
    "ins_nm": "Pemerintah Kab. Jayawijaya",
    "jp_nama": "CPNS",
    "formasi_nm": "ORANG ASLI PAPUA (OAP)",
    "jabatan_nm": "PENATA LAKSANA PENYEHATAN LINGKUNGAN PEMULA",
    "lokasi_nm": "Kabupaten Jayawijaya | DINAS LINGKUNGAN HIDUP | BIDANG PENGELOLAAN SAMPAH DAN LIMBAH B3 | SEKSI PENANGANAN SAMPAH",
    "jumlah_formasi": 2,
    "disable": 1,
    "gaji_min": "2200000",
    "gaji_max": "4600000",
    "jumlah_ms": 103,
    "kode_pend": "3171087",
    "nama_pend": "SMK TEKNIK KONSTRUKSI BATU DAN BETON"
  },
  {
    "formasi_id": "be9aafc1-ace5-4b2c-b326-f04f4c703c82",
    "ins_nm": "Pemerintah Kab. Jayawijaya",
    "jp_nama": "CPNS",
    "formasi_nm": "ORANG ASLI PAPUA (OAP)",
    "jabatan_nm": "PENATA LAKSANA PENYEHATAN LINGKUNGAN PEMULA",
    "lokasi_nm": "Kabupaten Jayawijaya | DINAS LINGKUNGAN HIDUP | BIDANG PENGENDALIAN PENCEMARAN & KERUSAKAN LINGKUNGAN HIDUP | SEKSI KERUSAKAN LINGKUNGAN",
    "jumlah_formasi": 2,
    "disable": 1,
    "gaji_min": "2200000",
    "gaji_max": "4600000",
    "jumlah_ms": 91,
    "kode_pend": "3171087",
    "nama_pend": "SMK TEKNIK KONSTRUKSI BATU DAN BETON"
  },
  {
    "formasi_id": "df4f5210-6266-4efe-8160-f1ac1aaa1599",
    "ins_nm": "Pemerintah Kab. Jayawijaya",
    "jp_nama": "CPNS",
    "formasi_nm": "ORANG ASLI PAPUA (OAP)",
    "jabatan_nm": "PENATA LAKSANA PENYEHATAN LINGKUNGAN PEMULA",
    "lokasi_nm": "Kabupaten Jayawijaya | DINAS PEKERJAAN UMUM DAN PENATAAN RUANG | Bidang Cipta Karya | SEKSI PERUMAHAN DAN PEMUKIMAN",
    "jumlah_formasi": 1,
    "disable": 1,
    "gaji_min": "2200000",
    "gaji_max": "4600000",
    "jumlah_ms": 133,
    "kode_pend": "3171087",
    "nama_pend": "SMK TEKNIK KONSTRUKSI BATU DAN BETON"
  },
  {
    "formasi_id": "f90bfdb6-ece3-4826-91e3-981de3821583",
    "ins_nm": "Pemerintah Kab. Jayawijaya",
    "jp_nama": "CPNS",
    "formasi_nm": "ORANG ASLI PAPUA (OAP)",
    "jabatan_nm": "PENATA LAKSANA PENYEHATAN LINGKUNGAN PEMULA",
    "lokasi_nm": "Kabupaten Jayawijaya | DINAS LINGKUNGAN HIDUP | BIDANG PENGENDALIAN PENCEMARAN & KERUSAKAN LINGKUNGAN HIDUP | SEKSI PENCEMARAN LINGKUNGAN",
    "jumlah_formasi": 2,
    "disable": 1,
    "gaji_min": "2200000",
    "gaji_max": "4600000",
    "jumlah_ms": 34,
    "kode_pend": "3171087",
    "nama_pend": "SMK TEKNIK KONSTRUKSI BATU DAN BETON"
  }
]